Workbook

Sheet Basic Info
A1: Name of Company | B1: HDFC Life Insurance Company Ltd.
A2: Scrip Code | B2: HDFCLIFE
A3: Duration of Analysis | B3: 2014-15 to 2023-24
A5: Name | B5: Kishan Maheshwari
A6: Course | B6: MBA (FMB)
A7: Roll No | B7: 2384130019
A8: Sec. | B8: I

Sheet Income Statement
A1: Narration | B1: Mar-14 | C1: Mar-15 | D1: Mar-16 | E1: Mar-17 | F1: Mar-18 | G1: Mar-19 | H1: Mar-20 | I1: Mar-21 | J1: Mar-22 | K1: Mar-23 | L1: Mar-24
A2: Sales | B2: 17166 | C2: 27215.02 | D2: 18140.55 | E2: 30646.61 | F2: 32259.93 | G2: 38854.68 | H2: 29380.4 | I2: 71528.03 | J2: 67125.82 | K2: 70207.08 | L2: 101481.8
A3: Expenses | B3: 16561 | C3: 26341.39 | D3: 17187.29 | E3: 29674.38 | F3: 31185.89 | G3: 37640.13 | H3: 28239.43 | I3: 70293.52 | J3: 66348.07 | K3: 70127.15 | L3: 100950.58
A4: Operating Profit | B4: 605 | C4: 873.63 | D4: 953.26 | E4: 972.23 | F4: 1074.04 | G4: 1214.55 | H4: 1140.97 | I4: 1234.51 | J4: 777.75 | K4: 79.93 | L4: 531.22
A5: Other Income | B5: 241 | C5: 78.91 | D5: 107.68 | E5: 138.98 | F5: 281.66 | G5: 135.65 | H5: 368.56 | I5: 445.05 | J5: 765.78 | K5: 1437.32 | L5: 524.81
A6: Depreciation | B6: 41 | C6: 42.72 | D6: 44.91 | E6: 41.24 | F6: 44.45 | G6: 45.24 | H6: 46.57 | I6: 50.89 | J6: 56.27 | K6: 75.93 | L6: 78.75
A7: Interest | B7: 11 | C7: -14.1 | D7: 8.1 | E7: 9.06 | F7: 10.76 | G7: 13.94 | H7: 0 | I7: 0 | J7: 0 | K7: 0 | L7: 0
A8: Profit before tax | B8: 794 | C8: 923.92 | D8: 1007.93 | E8: 1060.91 | F8: 1300.49 | G8: 1291.02 | H8: 1462.96 | I8: 1628.67 | J8: 1487.26 | K8: 1441.32 | L8: 977.28
A9: Tax | B9: 71.46 | C9: 138.41 | D9: 191.14 | E9: 173.99 | F9: 193.29 | G9: 13.09 | H9: 165.51 | I9: 267.8 | J9: 160.32 | K9: 73.05 | L9: -596.8
A10: Net profit | B10: 725 | C10: 785.51 | D10: 816.79 | E10: 886.92 | F10: 1107.2 | G10: 1277.93 | H10: 1297.44 | I10: 1360.87 | J10: 1326.93 | K10: 1368.28 | L10: 1574.08
A11: EPS | B11: 3.64 | C11: 3.9375909 | D11: 4.0935699 | E11: 4.4379284 | F11: 5.5038028 | G11: 6.3345395 | H11: 6.4267882 | I11: 6.7339799 | J11: 6.2810281 | K11: 6.3658695 | L11: 7.3182389
A12: Price to earning | B12: - | C12: - | D12: - | E12: - | F12: 82.570183 | G12: 59.751778 | H12: 68.673494 | I12: 103.38611 | J12: 85.686609 | K12: 78.418195 | L12: 86.544046
A13: Price | B13: - | C13: - | D13: - | E13: - | F13: 454.45 | G13: 378.5 | H13: 441.35 | I13: 696.2 | J13: 538.2 | K13: 499.2 | L13: 633.35
A15: RATIOS:
A16: Dividend Payout | C16: 0.17776986 | D16: 0.21986067 | E16: 0.24785775 | F16: 0.24710983 | G16: 0.25731456 | H16: 0 | I16: 0.29997722 | J16: 0.27066236 | K16: 0.29846961 | L16: 0.27329615
A17: OPM | C17: 0.032101024 | D17: 0.052548572 | E17: 0.0317239 | F17: 0.033293315 | G17: 0.031258783 | H17: 0.038834393 | I17: 0.017259108 | J17: 0.011586451 | K17: 0.0011384892 | L17: 0.0052346332

Sheet Balance Sheet
A1: Narration | B1: 41699 | C1: 42094 | D1: 42460 | E1: 42825 | F1: 43190 | G1: 43555 | H1: 43921 | I1: 44286 | J1: 44651 | K1: 45016 | L1: 45382
A2: Equity Share Capital | B2: 1995 | C2: 1994.88 | D2: 1995.29 | E2: 1998.48 | F2: 2011.74 | G2: 2017.38 | H2: 2018.8 | I2: 2020.94 | J2: 2112.62 | K2: 2149.4 | L2: 2150.94
A3: Reserves | B3: -67 | C3: 546.4 | D3: 1108.2 | E3: 1827.84 | F3: 2693.37 | G3: 3625.22 | H3: 4787.82 | I3: 6618.85 | J3: 13500.71 | K3: 10843.74 | L3: 12515.41
A4: Borrowings | B4: 0 | C4: 0 | D4: 0 | E4: 0 | F4: 0 | G4: 0 | H4: 0 | I4: 600 | J4: 600 | K4: 950 | L4: 950
A5: Other Liabilities | B5: 50347 | C5: 66767.24 | D5: 73440.89 | E5: 91270.25 | F5: 105777.71 | G5: 124377.81 | H5: 125417.23 | I5: 170415.25 | J5: 214521.12 | K5: 234126.11 | L5: 287070.6
A6: Total Liabilities | B6: 52275 | C6: 69308.52 | D6: 76544.38 | E6: 95096.57 | F6: 110482.82 | G6: 130020.41 | H6: 132223.85 | I6: 179655.04 | J6: 230734.45 | K6: 248069.25 | L6: 302686.95
A8: Net Block | B8: 279 | C8: 346.03 | D8: 335.2 | E8: 337.37 | F8: 336.42 | G8: 370.16 | H8: 322.3 | I8: 584.68 | J8: 6605.24 | K8: 997.2 | L8: 1548.99
A9: Capital Work in Progress | B9: 10 | C9: 6.44 | D9: 12.16 | E9: 16.09 | F9: 5.28 | G9: 10.19 | H9: 8.41 | I9: 14.24 | J9: 19.8 | K9: 30.79 | L9: 27.67
A10: Investments | B10: 50527 | C10: 67023.56 | D10: 74143.68 | E10: 91723.43 | F10: 106589.88 | G10: 124957.97 | H10: 127255.71 | I10: 173563.57 | J10: 216550.64 | K10: 238197.1 | L10: 291127.93
A11: Other Assets | B11: 1458 | C11: 1932.49 | D11: 2053.34 | E11: 3019.68 | F11: 3551.24 | G11: 4682.09 | H11: 4637.43 | I11: 5492.55 | J11: 7558.77 | K11: 8844.16 | L11: 9982.36
A12: Total Assets | B12: 52275 | C12: 69308.52 | D12: 76544.38 | E12: 95096.57 | F12: 110482.82 | G12: 130020.41 | H12: 132223.85 | I12: 179655.04 | J12: 230734.45 | K12: 248069.25 | L12: 302686.95
A14: Working Capital | C14: -64834.75 | D14: -71387.55 | E14: -88250.57 | F14: -102226.47 | G14: -119695.72 | H14: -120779.8 | I14: -164922.7 | J14: -206962.35 | K14: -225281.95 | L14: -277088.24
A15: Debtors | B15: 0 | C15: 0 | D15: 0 | E15: 0 | F15: 0 | G15: 205.5 | H15: 0 | I15: 0 | J15: 0 | K15: 0 | L15: 0
A16: Inventory | B16: 0 | C16: 0 | D16: 0 | E16: 0 | F16: 0 | G16: 0 | H16: 0 | I16: 0 | J16: 0 | K16: 0 | L16: 0
A18: Debtor Days | B18: 0 | C18: 0 | D18: 0 | E18: 0 | F18: 0 | G18: 1.9304624 | H18: 0 | I18: 0 | J18: 0 | K18: 0 | L18: 0
A19: Inventory Turnover | B19: 0 | C19: 0 | D19: 0 | E19: 0 | F19: 0 | G19: 0 | H19: 0 | I19: 0 | J19: 0 | K19: 0 | L19: 0

Sheet Comp. Statement
A1: =CONCATENATE("Comparative Income Statement of ",'Basic Info'!B1," [", 'Basic Info'!B2,"]"," (",'Basic Info'!B3,")") -> Comparative Income Statement of HDFC Life Insurance Company Ltd. [HDFCLIFE] (2014-15 to 2023-24)
A2: ='Income Statement'!A1 -> Narration | B2: ='Income Statement'!C1 -> Mar-15 | C2: ='Income Statement'!D1 -> Mar-16 | D2: ='Income Statement'!E1 -> Mar-17 | E2: ='Income Statement'!F1 -> Mar-18 | F2: ='Income Statement'!G1 -> Mar-19 | G2: ='Income Statement'!H1 -> Mar-20 | H2: ='Income Statement'!I1 -> Mar-21 | I2: ='Income Statement'!J1 -> Mar-22 | ... K2: ='Income Statement'!L1 -> Mar-24
A3: ='Income Statement'!A2 -> Sales | B3: =('Income Statement'!C2-'Income Statement'!B2)/'Income Statement'!B2 -> 0.58540254 | C3: =('Income Statement'!D2-'Income Statement'!C2)/'Income Statement'!C2 -> -0.3334361 | D3: =('Income Statement'!E2-'Income Statement'!D2)/'Income Statement'!D2 -> 0.68939806 | E3: =('Income Statement'!F2-'Income Statement'!E2)/'Income Statement'!E2 -> 0.05264269 | F3: =('Income Statement'!G2-'Income Statement'!F2)/'Income Statement'!F2 -> 0.20442543 | G3: =('Income Statement'!H2-'Income Statement'!G2)/'Income Statement'!G2 -> -0.24383884 | H3: =('Income Statement'!I2-'Income Statement'!H2)/'Income Statement'!H2 -> 1.4345492 | I3: =('Income Statement'!J2-'Income Statement'!I2)/'Income Statement'!I2 -> -0.061545243 | ... K3: =('Income Statement'!L2-'Income Statement'!K2)/'Income Statement'!K2 -> 0.4454639
A4: ='Income Statement'!A3 -> Expenses | B4: =('Income Statement'!C3-'Income Statement'!B3)/'Income Statement'!B3 -> 0.5905676 | C4: =('Income Statement'!D3-'Income Statement'!C3)/'Income Statement'!C3 -> -0.34751773 | D4: =('Income Statement'!E3-'Income Statement'!D3)/'Income Statement'!D3 -> 0.72653048 | E4: =('Income Statement'!F3-'Income Statement'!E3)/'Income Statement'!E3 -> 0.050936532 | F4: =('Income Statement'!G3-'Income Statement'!F3)/'Income Statement'!F3 -> 0.20696026 | G4: =('Income Statement'!H3-'Income Statement'!G3)/'Income Statement'!G3 -> -0.24975206 | H4: =('Income Statement'!I3-'Income Statement'!H3)/'Income Statement'!H3 -> 1.4891976 | I4: =('Income Statement'!J3-'Income Statement'!I3)/'Income Statement'!I3 -> -0.056128218 | ... K4: =('Income Statement'!L3-'Income Statement'!K3)/'Income Statement'!K3 -> 0.43953633
A5: ='Income Statement'!A4 -> Operating Profit | B5: =('Income Statement'!C4-'Income Statement'!B4)/'Income Statement'!B4 -> 0.44401653 | C5: =('Income Statement'!D4-'Income Statement'!C4)/'Income Statement'!C4 -> 0.091148427 | D5: =('Income Statement'!E4-'Income Statement'!D4)/'Income Statement'!D4 -> 0.019900132 | E5: =('Income Statement'!F4-'Income Statement'!E4)/'Income Statement'!E4 -> 0.10471802 | F5: =('Income Statement'!G4-'Income Statement'!F4)/'Income Statement'!F4 -> 0.13082381 | G5: =('Income Statement'!H4-'Income Statement'!G4)/'Income Statement'!G4 -> -0.060582109 | H5: =('Income Statement'!I4-'Income Statement'!H4)/'Income Statement'!H4 -> 0.081982874 | I5: =('Income Statement'!J4-'Income Statement'!I4)/'Income Statement'!I4 -> -0.36999295 | ... K5: =('Income Statement'!L4-'Income Statement'!K4)/'Income Statement'!K4 -> 5.6460653
A6: ='Income Statement'!A5 -> Other Income | B6: =('Income Statement'!C5-'Income Statement'!B5)/'Income Statement'!B5 -> -0.67257261 | C6: =('Income Statement'!D5-'Income Statement'!C5)/'Income Statement'!C5 -> 0.36459257 | D6: =('Income Statement'!E5-'Income Statement'!D5)/'Income Statement'!D5 -> 0.29067608 | E6: =('Income Statement'!F5-'Income Statement'!E5)/'Income Statement'!E5 -> 1.0266225 | F6: =('Income Statement'!G5-'Income Statement'!F5)/'Income Statement'!F5 -> -0.51839097 | G6: =('Income Statement'!H5-'Income Statement'!G5)/'Income Statement'!G5 -> 1.7169923 | H6: =('Income Statement'!I5-'Income Statement'!H5)/'Income Statement'!H5 -> 0.20753744 | I6: =('Income Statement'!J5-'Income Statement'!I5)/'Income Statement'!I5 -> 0.7206606 | ... K6: =('Income Statement'!L5-'Income Statement'!K5)/'Income Statement'!K5 -> -0.63486906
A7: ='Income Statement'!A6 -> Depreciation | B7: =('Income Statement'!C6-'Income Statement'!B6)/'Income Statement'!B6 -> 0.04195122 | C7: =('Income Statement'!D6-'Income Statement'!C6)/'Income Statement'!C6 -> 0.051264045 | D7: =('Income Statement'!E6-'Income Statement'!D6)/'Income Statement'!D6 -> -0.081718994 | E7: =('Income Statement'!F6-'Income Statement'!E6)/'Income Statement'!E6 -> 0.077837051 | F7: =('Income Statement'!G6-'Income Statement'!F6)/'Income Statement'!F6 -> 0.017772778 | G7: =('Income Statement'!H6-'Income Statement'!G6)/'Income Statement'!G6 -> 0.029398762 | H7: =('Income Statement'!I6-'Income Statement'!H6)/'Income Statement'!H6 -> 0.092763582 | I7: =('Income Statement'!J6-'Income Statement'!I6)/'Income Statement'!I6 -> 0.10571822 | ... K7: =('Income Statement'!L6-'Income Statement'!K6)/'Income Statement'!K6 -> 0.037139471
A8: ='Income Statement'!A7 -> Interest | B8: =('Income Statement'!C7-'Income Statement'!B7)/'Income Statement'!B7 -> -2.2818182 | C8: =('Income Statement'!D7-'Income Statement'!C7)/'Income Statement'!C7 -> -1.5744681 | D8: =('Income Statement'!E7-'Income Statement'!D7)/'Income Statement'!D7 -> 0.11851852 | E8: =('Income Statement'!F7-'Income Statement'!E7)/'Income Statement'!E7 -> 0.18763797 | F8: =('Income Statement'!G7-'Income Statement'!F7)/'Income Statement'!F7 -> 0.29553903 | G8: =('Income Statement'!H7-'Income Statement'!G7)/'Income Statement'!G7 -> -1 | H8: - | I8: - | J8: - | K8: -
A9: ='Income Statement'!A8 -> Profit before tax | B9: =('Income Statement'!C8-'Income Statement'!B8)/'Income Statement'!B8 -> 0.1636272 | C9: =('Income Statement'!D8-'Income Statement'!C8)/'Income Statement'!C8 -> 0.090927786 | D9: =('Income Statement'!E8-'Income Statement'!D8)/'Income Statement'!D8 -> 0.052563174 | E9: =('Income Statement'!F8-'Income Statement'!E8)/'Income Statement'!E8 -> 0.225825 | F9: =('Income Statement'!G8-'Income Statement'!F8)/'Income Statement'!F8 -> -0.0072818707 | G9: =('Income Statement'!H8-'Income Statement'!G8)/'Income Statement'!G8 -> 0.13318152 | H9: =('Income Statement'!I8-'Income Statement'!H8)/'Income Statement'!H8 -> 0.11327036 | I9: =('Income Statement'!J8-'Income Statement'!I8)/'Income Statement'!I8 -> -0.086825447 | ... K9: =('Income Statement'!L8-'Income Statement'!K8)/'Income Statement'!K8 -> -0.32195487
A10: ='Income Statement'!A9 -> Tax | B10: =('Income Statement'!C9-'Income Statement'!B9)/'Income Statement'!B9 -> 0.93688777 | C10: =('Income Statement'!D9-'Income Statement'!C9)/'Income Statement'!C9 -> 0.38096958 | D10: =('Income Statement'!E9-'Income Statement'!D9)/'Income Statement'!D9 -> -0.089724809 | E10: =('Income Statement'!F9-'Income Statement'!E9)/'Income Statement'!E9 -> 0.11092592 | F10: =('Income Statement'!G9-'Income Statement'!F9)/'Income Statement'!F9 -> -0.93227792 | G10: =('Income Statement'!H9-'Income Statement'!G9)/'Income Statement'!G9 -> 11.644003 | H10: =('Income Statement'!I9-'Income Statement'!H9)/'Income Statement'!H9 -> 0.61802912 | I10: =('Income Statement'!J9-'Income Statement'!I9)/'Income Statement'!I9 -> -0.40134429 | ... K10: =('Income Statement'!L9-'Income Statement'!K9)/'Income Statement'!K9 -> -9.1697467
A11: ='Income Statement'!A10 -> Net profit | B11: =('Income Statement'!C10-'Income Statement'!B10)/'Income Statement'!B10 -> 0.083462069 | C11: =('Income Statement'!D10-'Income Statement'!C10)/'Income Statement'!C10 -> 0.039821263 | D11: =('Income Statement'!E10-'Income Statement'!D10)/'Income Statement'!D10 -> 0.085860503 | E11: =('Income Statement'!F10-'Income Statement'!E10)/'Income Statement'!E10 -> 0.24836513 | F11: =('Income Statement'!G10-'Income Statement'!F10)/'Income Statement'!F10 -> 0.15419978 | G11: =('Income Statement'!H10-'Income Statement'!G10)/'Income Statement'!G10 -> 0.015266877 | H11: =('Income Statement'!I10-'Income Statement'!H10)/'Income Statement'!H10 -> 0.048888581 | I11: =('Income Statement'!J10-'Income Statement'!I10)/'Income Statement'!I10 -> -0.024939928 | ... K11: =('Income Statement'!L10-'Income Statement'!K10)/'Income Statement'!K10 -> 0.15040781
A12: ='Income Statement'!A11 -> EPS | B12: =('Income Statement'!C11-'Income Statement'!B11)/'Income Statement'!B11 -> 0.08175573 | C12: =('Income Statement'!D11-'Income Statement'!C11)/'Income Statement'!C11 -> 0.039612808 | D12: =('Income Statement'!E11-'Income Statement'!D11)/'Income Statement'!D11 -> 0.084121822 | E12: =('Income Statement'!F11-'Income Statement'!E11)/'Income Statement'!E11 -> 0.24017384 | F12: =('Income Statement'!G11-'Income Statement'!F11)/'Income Statement'!F11 -> 0.15093869 | G12: =('Income Statement'!H11-'Income Statement'!G11)/'Income Statement'!G11 -> 0.014562808 | H12: =('Income Statement'!I11-'Income Statement'!H11)/'Income Statement'!H11 -> 0.047798637 | I12: =('Income Statement'!J11-'Income Statement'!I11)/'Income Statement'!I11 -> -0.067263609 | ... K12: =('Income Statement'!L11-'Income Statement'!K11)/'Income Statement'!K11 -> 0.14960554
A13: ='Income Statement'!A12 -> Price to earning | B13: - | C13: - | D13: - | E13: - | F13: =('Income Statement'!G12-'Income Statement'!F12)/'Income Statement'!F12 -> -0.27635163 | G13: =('Income Statement'!H12-'Income Statement'!G12)/'Income Statement'!G12 -> 0.14931297 | H13: =('Income Statement'!I12-'Income Statement'!H12)/'Income Statement'!H12 -> 0.5054733 | I13: =('Income Statement'!J12-'Income Statement'!I12)/'Income Statement'!I12 -> -0.17119807 | J13: =('Income Statement'!K12-'Income Statement'!J12)/'Income Statement'!J12 -> -0.084825551 | K13: =('Income Statement'!L12-'Income Statement'!K12)/'Income Statement'!K12 -> 0.10362201
A14: ='Income Statement'!A13 -> Price | B14: - | C14: - | D14: - | E14: - | F14: =('Income Statement'!G13-'Income Statement'!F13)/'Income Statement'!F13 -> -0.1671251 | G14: =('Income Statement'!H13-'Income Statement'!G13)/'Income Statement'!G13 -> 0.1660502 | H14: =('Income Statement'!I13-'Income Statement'!H13)/'Income Statement'!H13 -> 0.57743288 | I14: =('Income Statement'!J13-'Income Statement'!I13)/'Income Statement'!I13 -> -0.22694628 | J14: =('Income Statement'!K13-'Income Statement'!J13)/'Income Statement'!J13 -> -0.072463768 | K14: =('Income Statement'!L13-'Income Statement'!K13)/'Income Statement'!K13 -> 0.26872997
A17: =CONCATENATE("Comparative Balance Sheet of ",'Basic Info'!B1," [", 'Basic Info'!B2,"]"," (",'Basic Info'!B3,")") -> Comparative Balance Sheet of HDFC Life Insurance Company Ltd. [HDFCLIFE] (2014-15 to 2023-24)
A18: ='Balance Sheet'!A1 -> Narration | B18: ='Balance Sheet'!C1 -> 42094 | C18: ='Balance Sheet'!D1 -> 42460 | D18: ='Balance Sheet'!E1 -> 42825 | E18: ='Balance Sheet'!F1 -> 43190 | F18: ='Balance Sheet'!G1 -> 43555 | G18: ='Balance Sheet'!H1 -> 43921 | H18: ='Balance Sheet'!I1 -> 44286 | I18: ='Balance Sheet'!J1 -> 44651 | ... K18: ='Balance Sheet'!L1 -> 45382
A19: ='Balance Sheet'!A2 -> Equity Share Capital | B19: =('Balance Sheet'!C2-'Balance Sheet'!B2)/'Balance Sheet'!B2 -> -6.0150376e-05 | C19: =('Balance Sheet'!D2-'Balance Sheet'!C2)/'Balance Sheet'!C2 -> 0.00020552615 | D19: =('Balance Sheet'!E2-'Balance Sheet'!D2)/'Balance Sheet'!D2 -> 0.0015987651 | E19: =('Balance Sheet'!F2-'Balance Sheet'!E2)/'Balance Sheet'!E2 -> 0.0066350426 | F19: =('Balance Sheet'!G2-'Balance Sheet'!F2)/'Balance Sheet'!F2 -> 0.0028035432 | G19: =('Balance Sheet'!H2-'Balance Sheet'!G2)/'Balance Sheet'!G2 -> 0.00070388325 | H19: =('Balance Sheet'!I2-'Balance Sheet'!H2)/'Balance Sheet'!H2 -> 0.0010600357 | I19: =('Balance Sheet'!J2-'Balance Sheet'!I2)/'Balance Sheet'!I2 -> 0.045365028 | ... K19: =('Balance Sheet'!L2-'Balance Sheet'!K2)/'Balance Sheet'!K2 -> 0.00071647902
A20: ='Balance Sheet'!A3 -> Reserves | B20: =('Balance Sheet'!C3-'Balance Sheet'!B3)/'Balance Sheet'!B3 -> -9.1552239 | C20: =('Balance Sheet'!D3-'Balance Sheet'!C3)/'Balance Sheet'!C3 -> 1.0281845 | D20: =('Balance Sheet'!E3-'Balance Sheet'!D3)/'Balance Sheet'!D3 -> 0.64937737 | E20: =('Balance Sheet'!F3-'Balance Sheet'!E3)/'Balance Sheet'!E3 -> 0.47352613 | F20: =('Balance Sheet'!G3-'Balance Sheet'!F3)/'Balance Sheet'!F3 -> 0.3459792 | G20: =('Balance Sheet'!H3-'Balance Sheet'!G3)/'Balance Sheet'!G3 -> 0.32069778 | H20: =('Balance Sheet'!I3-'Balance Sheet'!H3)/'Balance Sheet'!H3 -> 0.38243501 | I20: =('Balance Sheet'!J3-'Balance Sheet'!I3)/'Balance Sheet'!I3 -> 1.0397365 | ... K20: =('Balance Sheet'!L3-'Balance Sheet'!K3)/'Balance Sheet'!K3 -> 0.15415991
A21: ='Balance Sheet'!A4 -> Borrowings | B21: - | C21: - | D21: - | E21: - | F21: - | G21: - | H21: - | I21: =('Balance Sheet'!J4-'Balance Sheet'!I4)/'Balance Sheet'!I4 -> 0 | J21: =('Balance Sheet'!K4-'Balance Sheet'!J4)/'Balance Sheet'!J4 -> 0.58333333 | K21: =('Balance Sheet'!L4-'Balance Sheet'!K4)/'Balance Sheet'!K4 -> 0
A22: ='Balance Sheet'!A5 -> Other Liabilities | B22: =('Balance Sheet'!C5-'Balance Sheet'!B5)/'Balance Sheet'!B5 -> 0.32614138 | C22: =('Balance Sheet'!D5-'Balance Sheet'!C5)/'Balance Sheet'!C5 -> 0.099953959 | D22: =('Balance Sheet'!E5-'Balance Sheet'!D5)/'Balance Sheet'!D5 -> 0.24277157 | E22: =('Balance Sheet'!F5-'Balance Sheet'!E5)/'Balance Sheet'!E5 -> 0.15895059 | F22: =('Balance Sheet'!G5-'Balance Sheet'!F5)/'Balance Sheet'!F5 -> 0.17584139 | G22: =('Balance Sheet'!H5-'Balance Sheet'!G5)/'Balance Sheet'!G5 -> 0.0083569569 | H22: =('Balance Sheet'!I5-'Balance Sheet'!H5)/'Balance Sheet'!H5 -> 0.35878659 | I22: =('Balance Sheet'!J5-'Balance Sheet'!I5)/'Balance Sheet'!I5 -> 0.2588141 | ... K22: =('Balance Sheet'!L5-'Balance Sheet'!K5)/'Balance Sheet'!K5 -> 0.22613663
A23: =('Balance Sheet'!A6) -> Total Liabilities | B23: =('Balance Sheet'!C6-'Balance Sheet'!B6)/'Balance Sheet'!B6 -> 0.32584448 | C23: =('Balance Sheet'!D6-'Balance Sheet'!C6)/'Balance Sheet'!C6 -> 0.10440073 | D23: =('Balance Sheet'!E6-'Balance Sheet'!D6)/'Balance Sheet'!D6 -> 0.24237168 | E23: =('Balance Sheet'!F6-'Balance Sheet'!E6)/'Balance Sheet'!E6 -> 0.16179606 | F23: =('Balance Sheet'!G6-'Balance Sheet'!F6)/'Balance Sheet'!F6 -> 0.17683826 | G23: =('Balance Sheet'!H6-'Balance Sheet'!G6)/'Balance Sheet'!G6 -> 0.016946878 | H23: =('Balance Sheet'!I6-'Balance Sheet'!H6)/'Balance Sheet'!H6 -> 0.35871887 | I23: =('Balance Sheet'!J6-'Balance Sheet'!I6)/'Balance Sheet'!I6 -> 0.28431938 | ... K23: =('Balance Sheet'!L6-'Balance Sheet'!K6)/'Balance Sheet'!K6 -> 0.22017118
A24: ='Balance Sheet'!A8 -> Net Block | B24: =('Balance Sheet'!C8-'Balance Sheet'!B8)/'Balance Sheet'!B8 -> 0.2402509 | C24: =('Balance Sheet'!D8-'Balance Sheet'!C8)/'Balance Sheet'!C8 -> -0.031297864 | D24: =('Balance Sheet'!E8-'Balance Sheet'!D8)/'Balance Sheet'!D8 -> 0.006473747 | E24: =('Balance Sheet'!F8-'Balance Sheet'!E8)/'Balance Sheet'!E8 -> -0.0028158995 | F24: =('Balance Sheet'!G8-'Balance Sheet'!F8)/'Balance Sheet'!F8 -> 0.1002913 | G24: =('Balance Sheet'!H8-'Balance Sheet'!G8)/'Balance Sheet'!G8 -> -0.12929544 | H24: =('Balance Sheet'!I8-'Balance Sheet'!H8)/'Balance Sheet'!H8 -> 0.81408626 | I24: =('Balance Sheet'!J8-'Balance Sheet'!I8)/'Balance Sheet'!I8 -> 10.297188 | ... K24: =('Balance Sheet'!L8-'Balance Sheet'!K8)/'Balance Sheet'!K8 -> 0.55333935
A25: ='Balance Sheet'!A9 -> Capital Work in Progress | B25: =('Balance Sheet'!C9-'Balance Sheet'!B9)/'Balance Sheet'!B9 -> -0.356 | C25: =('Balance Sheet'!D9-'Balance Sheet'!C9)/'Balance Sheet'!C9 -> 0.88819876 | D25: =('Balance Sheet'!E9-'Balance Sheet'!D9)/'Balance Sheet'!D9 -> 0.32319079 | E25: =('Balance Sheet'!F9-'Balance Sheet'!E9)/'Balance Sheet'!E9 -> -0.67184587 | F25: =('Balance Sheet'!G9-'Balance Sheet'!F9)/'Balance Sheet'!F9 -> 0.92992424 | G25: =('Balance Sheet'!H9-'Balance Sheet'!G9)/'Balance Sheet'!G9 -> -0.17468106 | H25: =('Balance Sheet'!I9-'Balance Sheet'!H9)/'Balance Sheet'!H9 -> 0.69322235 | I25: =('Balance Sheet'!J9-'Balance Sheet'!I9)/'Balance Sheet'!I9 -> 0.39044944 | ... K25: =('Balance Sheet'!L9-'Balance Sheet'!K9)/'Balance Sheet'!K9 -> -0.1013316
A26: ='Balance Sheet'!A10 -> Investments | B26: =('Balance Sheet'!C10-'Balance Sheet'!B10)/'Balance Sheet'!B10 -> 0.32649 | C26: =('Balance Sheet'!D10-'Balance Sheet'!C10)/'Balance Sheet'!C10 -> 0.10623309 | D26: =('Balance Sheet'!E10-'Balance Sheet'!D10)/'Balance Sheet'!D10 -> 0.23710382 | E26: =('Balance Sheet'!F10-'Balance Sheet'!E10)/'Balance Sheet'!E10 -> 0.16207909 | F26: =('Balance Sheet'!G10-'Balance Sheet'!F10)/'Balance Sheet'!F10 -> 0.1723249 | G26: =('Balance Sheet'!H10-'Balance Sheet'!G10)/'Balance Sheet'!G10 -> 0.018388103 | H26: =('Balance Sheet'!I10-'Balance Sheet'!H10)/'Balance Sheet'!H10 -> 0.36389613 | I26: =('Balance Sheet'!J10-'Balance Sheet'!I10)/'Balance Sheet'!I10 -> 0.24767335 | ... K26: =('Balance Sheet'!L10-'Balance Sheet'!K10)/'Balance Sheet'!K10 -> 0.22221442
A27: ='Balance Sheet'!A11 -> Other Assets | B27: =('Balance Sheet'!C11-'Balance Sheet'!B11)/'Balance Sheet'!B11 -> 0.32543896 | C27: =('Balance Sheet'!D11-'Balance Sheet'!C11)/'Balance Sheet'!C11 -> 0.062535899 | D27: =('Balance Sheet'!E11-'Balance Sheet'!D11)/'Balance Sheet'!D11 -> 0.4706186 | E27: =('Balance Sheet'!F11-'Balance Sheet'!E11)/'Balance Sheet'!E11 -> 0.1760319 | F27: =('Balance Sheet'!G11-'Balance Sheet'!F11)/'Balance Sheet'!F11 -> 0.31843807 | G27: =('Balance Sheet'!H11-'Balance Sheet'!G11)/'Balance Sheet'!G11 -> -0.0095384753 | H27: =('Balance Sheet'!I11-'Balance Sheet'!H11)/'Balance Sheet'!H11 -> 0.18439524 | I27: =('Balance Sheet'!J11-'Balance Sheet'!I11)/'Balance Sheet'!I11 -> 0.37618592 | ... K27: =('Balance Sheet'!L11-'Balance Sheet'!K11)/'Balance Sheet'!K11 -> 0.12869509
A28: ='Balance Sheet'!A12 -> Total Assets | B28: =('Balance Sheet'!C12-'Balance Sheet'!B12)/'Balance Sheet'!B12 -> 0.32584448 | C28: =('Balance Sheet'!D12-'Balance Sheet'!C12)/'Balance Sheet'!C12 -> 0.10440073 | D28: =('Balance Sheet'!E12-'Balance Sheet'!D12)/'Balance Sheet'!D12 -> 0.24237168 | E28: =('Balance Sheet'!F12-'Balance Sheet'!E12)/'Balance Sheet'!E12 -> 0.16179606 | F28: =('Balance Sheet'!G12-'Balance Sheet'!F12)/'Balance Sheet'!F12 -> 0.17683826 | G28: =('Balance Sheet'!H12-'Balance Sheet'!G12)/'Balance Sheet'!G12 -> 0.016946878 | H28: =('Balance Sheet'!I12-'Balance Sheet'!H12)/'Balance Sheet'!H12 -> 0.35871887 | I28: =('Balance Sheet'!J12-'Balance Sheet'!I12)/'Balance Sheet'!I12 -> 0.28431938 | ... K28: =('Balance Sheet'!L12-'Balance Sheet'!K12)/'Balance Sheet'!K12 -> 0.22017118

Sheet Common Size
A1: =CONCATENATE("Common Size Income Statement of ",'Basic Info'!B1," [", 'Basic Info'!B2,"]"," (",'Basic Info'!B3,")") -> Common Size Income Statement of HDFC Life Insurance Company Ltd. [HDFCLIFE] (2014-15 to 2023-24)
A2: ='Income Statement'!A1 -> Narration | B2: ='Income Statement'!C1 -> Mar-15 | C2: ='Income Statement'!D1 -> Mar-16 | D2: ='Income Statement'!E1 -> Mar-17 | E2: ='Income Statement'!F1 -> Mar-18 | F2: ='Income Statement'!G1 -> Mar-19 | G2: ='Income Statement'!H1 -> Mar-20 | H2: ='Income Statement'!I1 -> Mar-21 | I2: ='Income Statement'!J1 -> Mar-22 | ... K2: ='Income Statement'!L1 -> Mar-24
A3: ='Income Statement'!A2 -> Sales | B3: ='Income Statement'!C2/'Income Statement'!C$2 -> 1 | C3: ='Income Statement'!D2/'Income Statement'!D$2 -> 1 | D3: ='Income Statement'!E2/'Income Statement'!E$2 -> 1 | E3: ='Income Statement'!F2/'Income Statement'!F$2 -> 1 | F3: ='Income Statement'!G2/'Income Statement'!G$2 -> 1 | G3: ='Income Statement'!H2/'Income Statement'!H$2 -> 1 | H3: ='Income Statement'!I2/'Income Statement'!I$2 -> 1 | I3: ='Income Statement'!J2/'Income Statement'!J$2 -> 1 | ... K3: ='Income Statement'!L2/'Income Statement'!L$2 -> 1
A4: ='Income Statement'!A3 -> Expenses | B4: ='Income Statement'!C3/'Income Statement'!C$2 -> 0.96789898 | C4: ='Income Statement'!D3/'Income Statement'!D$2 -> 0.94745143 | D4: ='Income Statement'!E3/'Income Statement'!E$2 -> 0.9682761 | E4: ='Income Statement'!F3/'Income Statement'!F$2 -> 0.96670669 | F4: ='Income Statement'!G3/'Income Statement'!G$2 -> 0.96874122 | G4: ='Income Statement'!H3/'Income Statement'!H$2 -> 0.96116561 | H4: ='Income Statement'!I3/'Income Statement'!I$2 -> 0.98274089 | I4: ='Income Statement'!J3/'Income Statement'!J$2 -> 0.98841355 | ... K4: ='Income Statement'!L3/'Income Statement'!L$2 -> 0.99476537
A5: ='Income Statement'!A4 -> Operating Profit | B5: ='Income Statement'!C4/'Income Statement'!C$2 -> 0.032101024 | C5: ='Income Statement'!D4/'Income Statement'!D$2 -> 0.052548572 | D5: ='Income Statement'!E4/'Income Statement'!E$2 -> 0.0317239 | E5: ='Income Statement'!F4/'Income Statement'!F$2 -> 0.033293315 | F5: ='Income Statement'!G4/'Income Statement'!G$2 -> 0.031258783 | G5: ='Income Statement'!H4/'Income Statement'!H$2 -> 0.038834393 | H5: ='Income Statement'!I4/'Income Statement'!I$2 -> 0.017259108 | I5: ='Income Statement'!J4/'Income Statement'!J$2 -> 0.011586451 | ... K5: ='Income Statement'!L4/'Income Statement'!L$2 -> 0.0052346332
A6: ='Income Statement'!A5 -> Other Income | B6: ='Income Statement'!C5/'Income Statement'!C$2 -> 0.0028995018 | C6: ='Income Statement'!D5/'Income Statement'!D$2 -> 0.0059358729 | D6: ='Income Statement'!E5/'Income Statement'!E$2 -> 0.0045349225 | E6: ='Income Statement'!F5/'Income Statement'!F$2 -> 0.0087309551 | F6: ='Income Statement'!G5/'Income Statement'!G$2 -> 0.0034912139 | G6: ='Income Statement'!H5/'Income Statement'!H$2 -> 0.012544417 | H6: ='Income Statement'!I5/'Income Statement'!I$2 -> 0.0062220363 | I6: ='Income Statement'!J5/'Income Statement'!J$2 -> 0.011408129 | ... K6: ='Income Statement'!L5/'Income Statement'!L$2 -> 0.0051714692
A7: ='Income Statement'!A6 -> Depreciation | B7: ='Income Statement'!C6/'Income Statement'!C$2 -> 0.0015697214 | C7: ='Income Statement'!D6/'Income Statement'!D$2 -> 0.0024756692 | D7: ='Income Statement'!E6/'Income Statement'!E$2 -> 0.0013456627 | E7: ='Income Statement'!F6/'Income Statement'!F$2 -> 0.0013778703 | F7: ='Income Statement'!G6/'Income Statement'!G$2 -> 0.0011643385 | G7: ='Income Statement'!H6/'Income Statement'!H$2 -> 0.0015850703 | H7: ='Income Statement'!I6/'Income Statement'!I$2 -> 0.00071146934 | I7: ='Income Statement'!J6/'Income Statement'!J$2 -> 0.00083827654 | ... K7: ='Income Statement'!L6/'Income Statement'!L$2 -> 0.00077600121
A8: ='Income Statement'!A7 -> Interest | B8: ='Income Statement'!C7/'Income Statement'!C$2 -> -0.00051809626 | C8: ='Income Statement'!D7/'Income Statement'!D$2 -> 0.00044651347 | D8: ='Income Statement'!E7/'Income Statement'!E$2 -> 0.00029562813 | E8: ='Income Statement'!F7/'Income Statement'!F$2 -> 0.00033354071 | F8: ='Income Statement'!G7/'Income Statement'!G$2 -> 0.00035877274 | G8: ='Income Statement'!H7/'Income Statement'!H$2 -> 0 | H8: ='Income Statement'!I7/'Income Statement'!I$2 -> 0 | I8: ='Income Statement'!J7/'Income Statement'!J$2 -> 0 | ... K8: ='Income Statement'!L7/'Income Statement'!L$2 -> 0
A9: ='Income Statement'!A8 -> Profit before tax | B9: ='Income Statement'!C8/'Income Statement'!C$2 -> 0.0339489 | C9: ='Income Statement'!D8/'Income Statement'!D$2 -> 0.055562262 | D9: ='Income Statement'!E8/'Income Statement'!E$2 -> 0.034617532 | E9: ='Income Statement'!F8/'Income Statement'!F$2 -> 0.040312859 | F9: ='Income Statement'!G8/'Income Statement'!G$2 -> 0.033226885 | G9: ='Income Statement'!H8/'Income Statement'!H$2 -> 0.04979374 | H9: ='Income Statement'!I8/'Income Statement'!I$2 -> 0.022769675 | I9: ='Income Statement'!J8/'Income Statement'!J$2 -> 0.022156303 | ... K9: ='Income Statement'!L8/'Income Statement'!L$2 -> 0.0096301012
A10: ='Income Statement'!A9 -> Tax | B10: ='Income Statement'!C9/'Income Statement'!C$2 -> 0.0050857945 | C10: ='Income Statement'!D9/'Income Statement'!D$2 -> 0.010536615 | D10: ='Income Statement'!E9/'Income Statement'!E$2 -> 0.0056773 | E10: ='Income Statement'!F9/'Income Statement'!F$2 -> 0.0059916435 | F10: ='Income Statement'!G9/'Income Statement'!G$2 -> 0.00033689635 | G10: ='Income Statement'!H9/'Income Statement'!H$2 -> 0.0056333474 | H10: ='Income Statement'!I9/'Income Statement'!I$2 -> 0.0037439868 | I10: ='Income Statement'!J9/'Income Statement'!J$2 -> 0.0023883507 | ... K10: ='Income Statement'!L9/'Income Statement'!L$2 -> -0.0058808575
A11: ='Income Statement'!A10 -> Net profit | B11: ='Income Statement'!C10/'Income Statement'!C$2 -> 0.028863106 | C11: ='Income Statement'!D10/'Income Statement'!D$2 -> 0.045025647 | D11: ='Income Statement'!E10/'Income Statement'!E$2 -> 0.028940232 | E11: ='Income Statement'!F10/'Income Statement'!F$2 -> 0.034321215 | F11: ='Income Statement'!G10/'Income Statement'!G$2 -> 0.032889989 | G11: ='Income Statement'!H10/'Income Statement'!H$2 -> 0.044160052 | H11: ='Income Statement'!I10/'Income Statement'!I$2 -> 0.019025688 | I11: ='Income Statement'!J10/'Income Statement'!J$2 -> 0.019767803 | ... K11: ='Income Statement'!L10/'Income Statement'!L$2 -> 0.015510959
A12: ='Income Statement'!A11 -> EPS | B12: ='Income Statement'!C11/'Income Statement'!C$2 -> 0.00014468447 | C12: ='Income Statement'!D11/'Income Statement'!D$2 -> 0.00022565853 | D12: ='Income Statement'!E11/'Income Statement'!E$2 -> 0.00014480977 | E12: ='Income Statement'!F11/'Income Statement'!F$2 -> 0.00017060802 | F12: ='Income Statement'!G11/'Income Statement'!G$2 -> 0.00016303157 | G12: ='Income Statement'!H11/'Income Statement'!H$2 -> 0.00021874407 | H12: ='Income Statement'!I11/'Income Statement'!I$2 -> 9.414463e-05 | I12: ='Income Statement'!J11/'Income Statement'!J$2 -> 9.357097e-05 | ... K12: ='Income Statement'!L11/'Income Statement'!L$2 -> 7.2113806e-05
A13: ='Income Statement'!A12 -> Price to earning | B13: - | C13: - | D13: - | E13: ='Income Statement'!F12/'Income Statement'!F$2 -> 0.0025595277 | F13: ='Income Statement'!G12/'Income Statement'!G$2 -> 0.0015378271 | G13: ='Income Statement'!H12/'Income Statement'!H$2 -> 0.0023373914 | H13: ='Income Statement'!I12/'Income Statement'!I$2 -> 0.001445393 | I13: ='Income Statement'!J12/'Income Statement'!J$2 -> 0.0012765074 | J13: ='Income Statement'!K12/'Income Statement'!K$2 -> 0.0011169557 | K13: ='Income Statement'!L12/'Income Statement'!L$2 -> 0.00085280361
A14: ='Income Statement'!A13 -> Price | B14: - | C14: - | D14: - | E14: ='Income Statement'!F13/'Income Statement'!F$2 -> 0.014087135 | F14: ='Income Statement'!G13/'Income Statement'!G$2 -> 0.0097414263 | G14: ='Income Statement'!H13/'Income Statement'!H$2 -> 0.015021919 | H14: ='Income Statement'!I13/'Income Statement'!I$2 -> 0.0097332472 | I14: ='Income Statement'!J13/'Income Statement'!J$2 -> 0.0080177791 | J14: ='Income Statement'!K13/'Income Statement'!K$2 -> 0.007110394 | K14: ='Income Statement'!L13/'Income Statement'!L$2 -> 0.0062410206
A17: =CONCATENATE("Common Size Balance Sheet Statement of ",'Basic Info'!B1," [",'Basic Info'!B2,"]"," (",'Basic Info'!B3,")") -> Common Size Balance Sheet Statement of HDFC Life Insurance Company Ltd. [HDFCLIFE] (2014-15 to 2023-24)
A18: ='Balance Sheet'!A1 -> Narration | B18: ='Balance Sheet'!C1 -> 42094 | C18: ='Balance Sheet'!D1 -> 42460 | D18: ='Balance Sheet'!E1 -> 42825 | E18: ='Balance Sheet'!F1 -> 43190 | F18: ='Balance Sheet'!G1 -> 43555 | G18: ='Balance Sheet'!H1 -> 43921 | H18: ='Balance Sheet'!I1 -> 44286 | I18: ='Balance Sheet'!J1 -> 44651 | ... K18: ='Balance Sheet'!L1 -> 45382
A19: ='Balance Sheet'!A2 -> Equity Share Capital | B19: ='Balance Sheet'!C2/'Balance Sheet'!C$6 -> 0.028782609 | C19: ='Balance Sheet'!D2/'Balance Sheet'!D$6 -> 0.0260671 | D19: ='Balance Sheet'!E2/'Balance Sheet'!E$6 -> 0.021015269 | E19: ='Balance Sheet'!F2/'Balance Sheet'!F$6 -> 0.018208623 | F19: ='Balance Sheet'!G2/'Balance Sheet'!G$6 -> 0.015515872 | G19: ='Balance Sheet'!H2/'Balance Sheet'!H$6 -> 0.015268047 | H19: ='Balance Sheet'!I2/'Balance Sheet'!I$6 -> 0.011249003 | I19: ='Balance Sheet'!J2/'Balance Sheet'!J$6 -> 0.0091560666 | ... K19: ='Balance Sheet'!L2/'Balance Sheet'!L$6 -> 0.0071061537
A20: ='Balance Sheet'!A3 -> Reserves | B20: ='Balance Sheet'!C3/'Balance Sheet'!C$6 -> 0.0078835906 | C20: ='Balance Sheet'!D3/'Balance Sheet'!D$6 -> 0.014477875 | D20: ='Balance Sheet'!E3/'Balance Sheet'!E$6 -> 0.019220883 | E20: ='Balance Sheet'!F3/'Balance Sheet'!F$6 -> 0.024378179 | F20: ='Balance Sheet'!G3/'Balance Sheet'!G$6 -> 0.02788193 | G20: ='Balance Sheet'!H3/'Balance Sheet'!H$6 -> 0.036209958 | H20: ='Balance Sheet'!I3/'Balance Sheet'!I$6 -> 0.036841995 | I20: ='Balance Sheet'!J3/'Balance Sheet'!J$6 -> 0.058511895 | ... K20: ='Balance Sheet'!L3/'Balance Sheet'!L$6 -> 0.041347703
A21: ='Balance Sheet'!A4 -> Borrowings | B21: ='Balance Sheet'!C4/'Balance Sheet'!C$6 -> 0 | C21: ='Balance Sheet'!D4/'Balance Sheet'!D$6 -> 0 | D21: ='Balance Sheet'!E4/'Balance Sheet'!E$6 -> 0 | E21: ='Balance Sheet'!F4/'Balance Sheet'!F$6 -> 0 | F21: ='Balance Sheet'!G4/'Balance Sheet'!G$6 -> 0 | G21: ='Balance Sheet'!H4/'Balance Sheet'!H$6 -> 0 | H21: ='Balance Sheet'!I4/'Balance Sheet'!I$6 -> 0.0033397337 | I21: ='Balance Sheet'!J4/'Balance Sheet'!J$6 -> 0.0026003919 | ... K21: ='Balance Sheet'!L4/'Balance Sheet'!L$6 -> 0.0031385562
A22: ='Balance Sheet'!A5 -> Other Liabilities | B22: ='Balance Sheet'!C5/'Balance Sheet'!C$6 -> 0.9633338 | C22: ='Balance Sheet'!D5/'Balance Sheet'!D$6 -> 0.95945502 | D22: ='Balance Sheet'!E5/'Balance Sheet'!E$6 -> 0.95976385 | E22: ='Balance Sheet'!F5/'Balance Sheet'!F$6 -> 0.9574132 | F22: ='Balance Sheet'!G5/'Balance Sheet'!G$6 -> 0.9566022 | G22: ='Balance Sheet'!H5/'Balance Sheet'!H$6 -> 0.948522 | H22: ='Balance Sheet'!I5/'Balance Sheet'!I$6 -> 0.94856927 | I22: ='Balance Sheet'!J5/'Balance Sheet'!J$6 -> 0.92973165 | ... K22: ='Balance Sheet'!L5/'Balance Sheet'!L$6 -> 0.94840759
A23: ='Balance Sheet'!A6 -> Total Liabilities | B23: ='Balance Sheet'!C6/'Balance Sheet'!C$6 -> 1 | C23: ='Balance Sheet'!D6/'Balance Sheet'!D$6 -> 1 | D23: ='Balance Sheet'!E6/'Balance Sheet'!E$6 -> 1 | E23: ='Balance Sheet'!F6/'Balance Sheet'!F$6 -> 1 | F23: ='Balance Sheet'!G6/'Balance Sheet'!G$6 -> 1 | G23: ='Balance Sheet'!H6/'Balance Sheet'!H$6 -> 1 | H23: ='Balance Sheet'!I6/'Balance Sheet'!I$6 -> 1 | I23: ='Balance Sheet'!J6/'Balance Sheet'!J$6 -> 1 | ... K23: ='Balance Sheet'!L6/'Balance Sheet'!L$6 -> 1
A24: ='Balance Sheet'!A8 -> Net Block | B24: ='Balance Sheet'!C8/'Balance Sheet'!C$12 -> 0.0049926041 | C24: ='Balance Sheet'!D8/'Balance Sheet'!D$12 -> 0.0043791589 | D24: ='Balance Sheet'!E8/'Balance Sheet'!E$12 -> 0.0035476569 | E24: ='Balance Sheet'!F8/'Balance Sheet'!F$12 -> 0.0030449983 | F24: ='Balance Sheet'!G8/'Balance Sheet'!G$12 -> 0.0028469376 | G24: ='Balance Sheet'!H8/'Balance Sheet'!H$12 -> 0.002437533 | H24: ='Balance Sheet'!I8/'Balance Sheet'!I$12 -> 0.0032544592 | I24: ='Balance Sheet'!J8/'Balance Sheet'!J$12 -> 0.028627021 | ... K24: ='Balance Sheet'!L8/'Balance Sheet'!L$12 -> 0.0051174654
A25: ='Balance Sheet'!A9 -> Capital Work in Progress | B25: ='Balance Sheet'!C9/'Balance Sheet'!C$12 -> 9.2917869e-05 | C25: ='Balance Sheet'!D9/'Balance Sheet'!D$12 -> 0.00015886209 | D25: ='Balance Sheet'!E9/'Balance Sheet'!E$12 -> 0.00016919643 | E25: ='Balance Sheet'!F9/'Balance Sheet'!F$12 -> 4.7790236e-05 | F25: ='Balance Sheet'!G9/'Balance Sheet'!G$12 -> 7.8372311e-05 | G25: ='Balance Sheet'!H9/'Balance Sheet'!H$12 -> 6.3604259e-05 | H25: ='Balance Sheet'!I9/'Balance Sheet'!I$12 -> 7.9263014e-05 | I25: ='Balance Sheet'!J9/'Balance Sheet'!J$12 -> 8.5812933e-05 | ... K25: ='Balance Sheet'!L9/'Balance Sheet'!L$12 -> 9.1414579e-05
A26: ='Balance Sheet'!A10 -> Investments | B26: ='Balance Sheet'!C10/'Balance Sheet'!C$12 -> 0.96703205 | C26: ='Balance Sheet'!D10/'Balance Sheet'!D$12 -> 0.9686365 | D26: ='Balance Sheet'!E10/'Balance Sheet'!E$12 -> 0.96452932 | E26: ='Balance Sheet'!F10/'Balance Sheet'!F$12 -> 0.9647643 | F26: ='Balance Sheet'!G10/'Balance Sheet'!G$12 -> 0.96106427 | G26: ='Balance Sheet'!H10/'Balance Sheet'!H$12 -> 0.96242629 | H26: ='Balance Sheet'!I10/'Balance Sheet'!I$12 -> 0.96609352 | I26: ='Balance Sheet'!J10/'Balance Sheet'!J$12 -> 0.93852756 | ... K26: ='Balance Sheet'!L10/'Balance Sheet'!L$12 -> 0.96181196
A27: ='Balance Sheet'!A11 -> Other Assets | B27: ='Balance Sheet'!C11/'Balance Sheet'!C$12 -> 0.027882431 | C27: ='Balance Sheet'!D11/'Balance Sheet'!D$12 -> 0.026825483 | D27: ='Balance Sheet'!E11/'Balance Sheet'!E$12 -> 0.031753827 | E27: ='Balance Sheet'!F11/'Balance Sheet'!F$12 -> 0.032142916 | F27: ='Balance Sheet'!G11/'Balance Sheet'!G$12 -> 0.036010423 | G27: ='Balance Sheet'!H11/'Balance Sheet'!H$12 -> 0.035072568 | H27: ='Balance Sheet'!I11/'Balance Sheet'!I$12 -> 0.030572758 | I27: ='Balance Sheet'!J11/'Balance Sheet'!J$12 -> 0.032759607 | ... K27: ='Balance Sheet'!L11/'Balance Sheet'!L$12 -> 0.032979156
A28: ='Balance Sheet'!A12 -> Total Assets | B28: ='Balance Sheet'!C12/'Balance Sheet'!C$12 -> 1 | C28: ='Balance Sheet'!D12/'Balance Sheet'!D$12 -> 1 | D28: ='Balance Sheet'!E12/'Balance Sheet'!E$12 -> 1 | E28: ='Balance Sheet'!F12/'Balance Sheet'!F$12 -> 1 | F28: ='Balance Sheet'!G12/'Balance Sheet'!G$12 -> 1 | G28: ='Balance Sheet'!H12/'Balance Sheet'!H$12 -> 1 | H28: ='Balance Sheet'!I12/'Balance Sheet'!I$12 -> 1 | I28: ='Balance Sheet'!J12/'Balance Sheet'!J$12 -> 1 | ... K28: ='Balance Sheet'!L12/'Balance Sheet'!L$12 -> 1

Sheet Trend Analysis
A1: =CONCATENATE("Income Statement Trend Analysis of ",'Basic Info'!B1," [", 'Basic Info'!B2,"]"," (",'Basic Info'!B3,")") -> Income Statement Trend Analysis of HDFC Life Insurance Company Ltd. [HDFCLIFE] (2014-15 to 2023-24)
A2: ='Income Statement'!A1 -> Narration | B2: ='Income Statement'!C1 -> Mar-15 | C2: ='Income Statement'!D1 -> Mar-16 | D2: ='Income Statement'!E1 -> Mar-17 | E2: ='Income Statement'!F1 -> Mar-18 | F2: ='Income Statement'!G1 -> Mar-19 | G2: ='Income Statement'!H1 -> Mar-20 | H2: ='Income Statement'!I1 -> Mar-21 | I2: ='Income Statement'!J1 -> Mar-22 | ... K2: ='Income Statement'!L1 -> Mar-24
A3: ='Income Statement'!A2 -> Sales | B3: ='Income Statement'!C2/'Income Statement'!$C2 -> 1 | C3: ='Income Statement'!D2/'Income Statement'!$C2 -> 0.6665639 | D3: ='Income Statement'!E2/'Income Statement'!$C2 -> 1.1260918 | E3: ='Income Statement'!F2/'Income Statement'!$C2 -> 1.1853723 | F3: ='Income Statement'!G2/'Income Statement'!$C2 -> 1.4276925 | G3: ='Income Statement'!H2/'Income Statement'!$C2 -> 1.0795656 | H3: ='Income Statement'!I2/'Income Statement'!$C2 -> 2.6282556 | I3: ='Income Statement'!J2/'Income Statement'!$C2 -> 2.466499 | ... K3: ='Income Statement'!L2/'Income Statement'!$C2 -> 3.7288894
A4: ='Income Statement'!A3 -> Expenses | B4: ='Income Statement'!C3/'Income Statement'!$C3 -> 1 | C4: ='Income Statement'!D3/'Income Statement'!$C3 -> 0.65248227 | D4: ='Income Statement'!E3/'Income Statement'!$C3 -> 1.1265305 | E4: ='Income Statement'!F3/'Income Statement'!$C3 -> 1.1839121 | F4: ='Income Statement'!G3/'Income Statement'!$C3 -> 1.4289348 | G4: ='Income Statement'!H3/'Income Statement'!$C3 -> 1.0720554 | H4: ='Income Statement'!I3/'Income Statement'!$C3 -> 2.6685577 | I4: ='Income Statement'!J3/'Income Statement'!$C3 -> 2.5187763 | ... K4: ='Income Statement'!L3/'Income Statement'!$C3 -> 3.8323938
A5: ='Income Statement'!A4 -> Operating Profit | B5: ='Income Statement'!C4/'Income Statement'!$C4 -> 1 | C5: ='Income Statement'!D4/'Income Statement'!$C4 -> 1.0911484 | D5: ='Income Statement'!E4/'Income Statement'!$C4 -> 1.1128624 | E5: ='Income Statement'!F4/'Income Statement'!$C4 -> 1.2293992 | F5: ='Income Statement'!G4/'Income Statement'!$C4 -> 1.3902339 | G5: ='Income Statement'!H4/'Income Statement'!$C4 -> 1.3060106 | H5: ='Income Statement'!I4/'Income Statement'!$C4 -> 1.4130811 | I5: ='Income Statement'!J4/'Income Statement'!$C4 -> 0.89025102 | ... K5: ='Income Statement'!L4/'Income Statement'!$C4 -> 0.60806062
A6: ='Income Statement'!A5 -> Other Income | B6: ='Income Statement'!C5/'Income Statement'!$C5 -> 1 | C6: ='Income Statement'!D5/'Income Statement'!$C5 -> 1.3645926 | D6: ='Income Statement'!E5/'Income Statement'!$C5 -> 1.761247 | E6: ='Income Statement'!F5/'Income Statement'!$C5 -> 3.5693828 | F6: ='Income Statement'!G5/'Income Statement'!$C5 -> 1.719047 | G6: ='Income Statement'!H5/'Income Statement'!$C5 -> 4.6706374 | H6: ='Income Statement'!I5/'Income Statement'!$C5 -> 5.6399696 | I6: ='Income Statement'!J5/'Income Statement'!$C5 -> 9.7044735 | ... K6: ='Income Statement'!L5/'Income Statement'!$C5 -> 6.6507414
A7: ='Income Statement'!A6 -> Depreciation | B7: ='Income Statement'!C6/'Income Statement'!$C6 -> 1 | C7: ='Income Statement'!D6/'Income Statement'!$C6 -> 1.051264 | D7: ='Income Statement'!E6/'Income Statement'!$C6 -> 0.96535581 | E7: ='Income Statement'!F6/'Income Statement'!$C6 -> 1.0404963 | F7: ='Income Statement'!G6/'Income Statement'!$C6 -> 1.0589888 | G7: ='Income Statement'!H6/'Income Statement'!$C6 -> 1.0901217 | H7: ='Income Statement'!I6/'Income Statement'!$C6 -> 1.1912453 | I7: ='Income Statement'!J6/'Income Statement'!$C6 -> 1.3171816 | ... K7: ='Income Statement'!L6/'Income Statement'!$C6 -> 1.8433989
A8: ='Income Statement'!A7 -> Interest | B8: ='Income Statement'!C7/'Income Statement'!$C7 -> 1 | C8: ='Income Statement'!D7/'Income Statement'!$C7 -> -0.57446809 | D8: ='Income Statement'!E7/'Income Statement'!$C7 -> -0.64255319 | E8: ='Income Statement'!F7/'Income Statement'!$C7 -> -0.76312057 | F8: ='Income Statement'!G7/'Income Statement'!$C7 -> -0.98865248 | G8: ='Income Statement'!H7/'Income Statement'!$C7 -> 0 | H8: ='Income Statement'!I7/'Income Statement'!$C7 -> 0 | I8: ='Income Statement'!J7/'Income Statement'!$C7 -> 0 | ... K8: ='Income Statement'!L7/'Income Statement'!$C7 -> 0
A9: ='Income Statement'!A8 -> Profit before tax | B9: ='Income Statement'!C8/'Income Statement'!$C8 -> 1 | C9: ='Income Statement'!D8/'Income Statement'!$C8 -> 1.0909278 | D9: ='Income Statement'!E8/'Income Statement'!$C8 -> 1.1482704 | E9: ='Income Statement'!F8/'Income Statement'!$C8 -> 1.4075786 | F9: ='Income Statement'!G8/'Income Statement'!$C8 -> 1.3973288 | G9: ='Income Statement'!H8/'Income Statement'!$C8 -> 1.5834271 | H9: ='Income Statement'!I8/'Income Statement'!$C8 -> 1.7627825 | I9: ='Income Statement'!J8/'Income Statement'!$C8 -> 1.6097281 | ... K9: ='Income Statement'!L8/'Income Statement'!$C8 -> 1.0577539
A10: ='Income Statement'!A9 -> Tax | B10: ='Income Statement'!C9/'Income Statement'!$C9 -> 1 | C10: ='Income Statement'!D9/'Income Statement'!$C9 -> 1.3809696 | D10: ='Income Statement'!E9/'Income Statement'!$C9 -> 1.2570624 | E10: ='Income Statement'!F9/'Income Statement'!$C9 -> 1.3965031 | F10: ='Income Statement'!G9/'Income Statement'!$C9 -> 0.094574091 | G10: ='Income Statement'!H9/'Income Statement'!$C9 -> 1.1957951 | H10: ='Income Statement'!I9/'Income Statement'!$C9 -> 1.9348313 | I10: ='Income Statement'!J9/'Income Statement'!$C9 -> 1.1582978 | ... K10: ='Income Statement'!L9/'Income Statement'!$C9 -> -4.3118272
A11: ='Income Statement'!A10 -> Net profit | B11: ='Income Statement'!C10/'Income Statement'!$C10 -> 1 | C11: ='Income Statement'!D10/'Income Statement'!$C10 -> 1.0398213 | D11: ='Income Statement'!E10/'Income Statement'!$C10 -> 1.1291008 | E11: ='Income Statement'!F10/'Income Statement'!$C10 -> 1.4095301 | F11: ='Income Statement'!G10/'Income Statement'!$C10 -> 1.6268794 | G11: ='Income Statement'!H10/'Income Statement'!$C10 -> 1.6517167 | H11: ='Income Statement'!I10/'Income Statement'!$C10 -> 1.7324668 | I11: ='Income Statement'!J10/'Income Statement'!$C10 -> 1.6892592 | ... K11: ='Income Statement'!L10/'Income Statement'!$C10 -> 2.0038956
A12: ='Income Statement'!A11 -> EPS | B12: ='Income Statement'!C11/'Income Statement'!$C11 -> 1 | C12: ='Income Statement'!D11/'Income Statement'!$C11 -> 1.0396128 | D12: ='Income Statement'!E11/'Income Statement'!$C11 -> 1.1270669 | E12: ='Income Statement'!F11/'Income Statement'!$C11 -> 1.3977589 | F12: ='Income Statement'!G11/'Income Statement'!$C11 -> 1.6087348 | G12: ='Income Statement'!H11/'Income Statement'!$C11 -> 1.6321625 | H12: ='Income Statement'!I11/'Income Statement'!$C11 -> 1.7101777 | I12: ='Income Statement'!J11/'Income Statement'!$C11 -> 1.5951449 | ... K12: ='Income Statement'!L11/'Income Statement'!$C11 -> 1.8585575
A13: ='Income Statement'!A12 -> Price to earning | B13: - | C13: - | D13: - | E13: - | F13: - | G13: - | H13: - | I13: - | J13: - | K13: -
A14: ='Income Statement'!A13 -> Price | B14: - | C14: - | D14: - | E14: - | F14: - | G14: - | H14: - | I14: - | J14: - | K14: -
A17: =CONCATENATE("Balance Sheet Trend Analysis of ",'Basic Info'!B1," [", 'Basic Info'!B2,"]"," (",'Basic Info'!B3,")") -> Balance Sheet Trend Analysis of HDFC Life Insurance Company Ltd. [HDFCLIFE] (2014-15 to 2023-24)
A18: ='Balance Sheet'!A1 -> Narration | B18: ='Balance Sheet'!C1 -> 42094 | C18: ='Balance Sheet'!D1 -> 42460 | D18: ='Balance Sheet'!E1 -> 42825 | E18: ='Balance Sheet'!F1 -> 43190 | F18: ='Balance Sheet'!G1 -> 43555 | G18: ='Balance Sheet'!H1 -> 43921 | H18: ='Balance Sheet'!I1 -> 44286 | I18: ='Balance Sheet'!J1 -> 44651 | ... K18: ='Balance Sheet'!L1 -> 45382
A19: ='Balance Sheet'!A2 -> Equity Share Capital | B19: ='Balance Sheet'!C2/'Balance Sheet'!$C2 -> 1 | C19: ='Balance Sheet'!D2/'Balance Sheet'!$C2 -> 1.0002055 | D19: ='Balance Sheet'!E2/'Balance Sheet'!$C2 -> 1.0018046 | E19: ='Balance Sheet'!F2/'Balance Sheet'!$C2 -> 1.0084516 | F19: ='Balance Sheet'!G2/'Balance Sheet'!$C2 -> 1.0112789 | G19: ='Balance Sheet'!H2/'Balance Sheet'!$C2 -> 1.0119907 | H19: ='Balance Sheet'!I2/'Balance Sheet'!$C2 -> 1.0130634 | I19: ='Balance Sheet'!J2/'Balance Sheet'!$C2 -> 1.0590211 | ... K19: ='Balance Sheet'!L2/'Balance Sheet'!$C2 -> 1.0782303
A20: ='Balance Sheet'!A3 -> Reserves | B20: ='Balance Sheet'!C3/'Balance Sheet'!$C3 -> 1 | C20: ='Balance Sheet'!D3/'Balance Sheet'!$C3 -> 2.0281845 | D20: ='Balance Sheet'!E3/'Balance Sheet'!$C3 -> 3.3452416 | E20: ='Balance Sheet'!F3/'Balance Sheet'!$C3 -> 4.9293009 | F20: ='Balance Sheet'!G3/'Balance Sheet'!$C3 -> 6.6347365 | G20: ='Balance Sheet'!H3/'Balance Sheet'!$C3 -> 8.7624817 | H20: ='Balance Sheet'!I3/'Balance Sheet'!$C3 -> 12.113561 | I20: ='Balance Sheet'!J3/'Balance Sheet'!$C3 -> 24.708474 | ... K20: ='Balance Sheet'!L3/'Balance Sheet'!$C3 -> 22.905216
A21: ='Balance Sheet'!A4 -> Borrowings | B21: - | C21: - | D21: - | E21: - | F21: - | G21: - | H21: - | I21: - | J21: - | K21: -
A22: ='Balance Sheet'!A5 -> Other Liabilities | B22: ='Balance Sheet'!C5/'Balance Sheet'!$C5 -> 1 | C22: ='Balance Sheet'!D5/'Balance Sheet'!$C5 -> 1.099954 | D22: ='Balance Sheet'!E5/'Balance Sheet'!$C5 -> 1.3669915 | E22: ='Balance Sheet'!F5/'Balance Sheet'!$C5 -> 1.5842756 | F22: ='Balance Sheet'!G5/'Balance Sheet'!$C5 -> 1.8628568 | G22: ='Balance Sheet'!H5/'Balance Sheet'!$C5 -> 1.8784247 | H22: ='Balance Sheet'!I5/'Balance Sheet'!$C5 -> 2.5523782 | I22: ='Balance Sheet'!J5/'Balance Sheet'!$C5 -> 3.2129697 | ... K22: ='Balance Sheet'!L5/'Balance Sheet'!$C5 -> 4.2995727
A23: ='Balance Sheet'!A6 -> Total Liabilities | B23: ='Balance Sheet'!C6/'Balance Sheet'!$C6 -> 1 | C23: ='Balance Sheet'!D6/'Balance Sheet'!$C6 -> 1.1044007 | D23: ='Balance Sheet'!E6/'Balance Sheet'!$C6 -> 1.3720762 | E23: ='Balance Sheet'!F6/'Balance Sheet'!$C6 -> 1.5940727 | F23: ='Balance Sheet'!G6/'Balance Sheet'!$C6 -> 1.8759658 | G23: ='Balance Sheet'!H6/'Balance Sheet'!$C6 -> 1.9077575 | H23: ='Balance Sheet'!I6/'Balance Sheet'!$C6 -> 2.5921061 | I23: ='Balance Sheet'!J6/'Balance Sheet'!$C6 -> 3.3290922 | ... K23: ='Balance Sheet'!L6/'Balance Sheet'!$C6 -> 4.3672401
A24: ='Balance Sheet'!A8 -> Net Block | B24: ='Balance Sheet'!C8/'Balance Sheet'!$C8 -> 1 | C24: ='Balance Sheet'!D8/'Balance Sheet'!$C8 -> 0.96870214 | D24: ='Balance Sheet'!E8/'Balance Sheet'!$C8 -> 0.97497327 | E24: ='Balance Sheet'!F8/'Balance Sheet'!$C8 -> 0.97222784 | F24: ='Balance Sheet'!G8/'Balance Sheet'!$C8 -> 1.0697338 | G24: ='Balance Sheet'!H8/'Balance Sheet'!$C8 -> 0.93142213 | H24: ='Balance Sheet'!I8/'Balance Sheet'!$C8 -> 1.6896801 | I24: ='Balance Sheet'!J8/'Balance Sheet'!$C8 -> 19.088634 | ... K24: ='Balance Sheet'!L8/'Balance Sheet'!$C8 -> 4.4764616
A25: ='Balance Sheet'!A9 -> Capital Work in Progress | B25: ='Balance Sheet'!C9/'Balance Sheet'!$C9 -> 1 | C25: ='Balance Sheet'!D9/'Balance Sheet'!$C9 -> 1.8881988 | D25: ='Balance Sheet'!E9/'Balance Sheet'!$C9 -> 2.4984472 | E25: ='Balance Sheet'!F9/'Balance Sheet'!$C9 -> 0.81987578 | F25: ='Balance Sheet'!G9/'Balance Sheet'!$C9 -> 1.5822981 | G25: ='Balance Sheet'!H9/'Balance Sheet'!$C9 -> 1.3059006 | H25: ='Balance Sheet'!I9/'Balance Sheet'!$C9 -> 2.2111801 | I25: ='Balance Sheet'!J9/'Balance Sheet'!$C9 -> 3.0745342 | ... K25: ='Balance Sheet'!L9/'Balance Sheet'!$C9 -> 4.2965839
A26: ='Balance Sheet'!A10 -> Investments | B26: ='Balance Sheet'!C10/'Balance Sheet'!$C10 -> 1 | C26: ='Balance Sheet'!D10/'Balance Sheet'!$C10 -> 1.1062331 | D26: ='Balance Sheet'!E10/'Balance Sheet'!$C10 -> 1.3685252 | E26: ='Balance Sheet'!F10/'Balance Sheet'!$C10 -> 1.5903345 | F26: ='Balance Sheet'!G10/'Balance Sheet'!$C10 -> 1.8643887 | G26: ='Balance Sheet'!H10/'Balance Sheet'!$C10 -> 1.8986713 | H26: ='Balance Sheet'!I10/'Balance Sheet'!$C10 -> 2.5895904 | I26: ='Balance Sheet'!J10/'Balance Sheet'!$C10 -> 3.230963 | ... K26: ='Balance Sheet'!L10/'Balance Sheet'!$C10 -> 4.3436656
A27: ='Balance Sheet'!A11 -> Other Assets | B27: ='Balance Sheet'!C11/'Balance Sheet'!$C11 -> 1 | C27: ='Balance Sheet'!D11/'Balance Sheet'!$C11 -> 1.0625359 | D27: ='Balance Sheet'!E11/'Balance Sheet'!$C11 -> 1.5625851 | E27: ='Balance Sheet'!F11/'Balance Sheet'!$C11 -> 1.8376499 | F27: ='Balance Sheet'!G11/'Balance Sheet'!$C11 -> 2.4228275 | G27: ='Balance Sheet'!H11/'Balance Sheet'!$C11 -> 2.3997175 | H27: ='Balance Sheet'!I11/'Balance Sheet'!$C11 -> 2.8422139 | I27: ='Balance Sheet'!J11/'Balance Sheet'!$C11 -> 3.9114148 | ... K27: ='Balance Sheet'!L11/'Balance Sheet'!$C11 -> 5.1655429
A28: ='Balance Sheet'!A12 -> Total Assets | B28: ='Balance Sheet'!C12/'Balance Sheet'!$C12 -> 1 | C28: ='Balance Sheet'!D12/'Balance Sheet'!$C12 -> 1.1044007 | D28: ='Balance Sheet'!E12/'Balance Sheet'!$C12 -> 1.3720762 | E28: ='Balance Sheet'!F12/'Balance Sheet'!$C12 -> 1.5940727 | F28: ='Balance Sheet'!G12/'Balance Sheet'!$C12 -> 1.8759658 | G28: ='Balance Sheet'!H12/'Balance Sheet'!$C12 -> 1.9077575 | H28: ='Balance Sheet'!I12/'Balance Sheet'!$C12 -> 2.5921061 | I28: ='Balance Sheet'!J12/'Balance Sheet'!$C12 -> 3.3290922 | ... K28: ='Balance Sheet'!L12/'Balance Sheet'!$C12 -> 4.3672401

Sheet Ratios
A1: Calculation of Financial Ratios
A2: Year | B2: Net Profit | C2: Euity (Start) | D2: Equity (End) | E2: Average Shareholder Equity | F2: ROE | G2: Assets (Start) | H2: Assets (End) | I2: Average Assets | J2: ROA
A3: 2015 | B3: =+'Income Statement'!C10 -> 785.51 | C3: =+'Balance Sheet'!B2+'Balance Sheet'!B3 -> 1928 | D3: =+'Balance Sheet'!C2+'Balance Sheet'!C3 -> 2541.28 | E3: =+(C3+D3)/2 -> 2234.64 | F3: =+(B3/E3)*100 -> 35.151523 | G3: =+'Balance Sheet'!B12 -> 52275 | H3: =+'Balance Sheet'!C12 -> 69308.52 | I3: =+(G3+H3)/2 -> 60791.76 | J3: =+(B3/I3)*100 -> 1.2921324
A4: =+A3+1 -> 2016 | B4: =+'Income Statement'!D10 -> 816.79 | C4: =+'Balance Sheet'!C2+'Balance Sheet'!C3 -> 2541.28 | D4: =+'Balance Sheet'!D2+'Balance Sheet'!D3 -> 3103.49 | E4: =+(C4+D4)/2 -> 2822.385 | F4: =+(B4/E4)*100 -> 28.939709 | G4: =+'Balance Sheet'!C12 -> 69308.52 | H4: =+'Balance Sheet'!D12 -> 76544.38 | I4: =+(G4+H4)/2 -> 72926.45 | J4: =+(B4/I4)*100 -> 1.1200189
A5: =+A4+1 -> 2017 | B5: =+'Income Statement'!E10 -> 886.92 | C5: =+'Balance Sheet'!D2+'Balance Sheet'!D3 -> 3103.49 | D5: =+'Balance Sheet'!E2+'Balance Sheet'!E3 -> 3826.32 | E5: =+(C5+D5)/2 -> 3464.905 | F5: =+(B5/E5)*100 -> 25.597239 | G5: =+'Balance Sheet'!D12 -> 76544.38 | H5: =+'Balance Sheet'!E12 -> 95096.57 | I5: =+(G5+H5)/2 -> 85820.475 | J5: =+(B5/I5)*100 -> 1.0334597
A6: =+A5+1 -> 2018 | B6: =+'Income Statement'!F10 -> 1107.2 | C6: =+'Balance Sheet'!E2+'Balance Sheet'!E3 -> 3826.32 | D6: =+'Balance Sheet'!F2+'Balance Sheet'!F3 -> 4705.11 | E6: =+(C6+D6)/2 -> 4265.715 | F6: =+(B6/E6)*100 -> 25.955789 | G6: =+'Balance Sheet'!E12 -> 95096.57 | H6: =+'Balance Sheet'!F12 -> 110482.82 | I6: =+(G6+H6)/2 -> 102789.7 | J6: =+(B6/I6)*100 -> 1.0771508
A7: =+A6+1 -> 2019 | B7: =+'Income Statement'!G10 -> 1277.93 | C7: =+'Balance Sheet'!F2+'Balance Sheet'!F3 -> 4705.11 | D7: =+'Balance Sheet'!G2+'Balance Sheet'!G3 -> 5642.6 | E7: =+(C7+D7)/2 -> 5173.855 | F7: =+(B7/E7)*100 -> 24.699764 | G7: =+'Balance Sheet'!F12 -> 110482.82 | H7: =+'Balance Sheet'!G12 -> 130020.41 | I7: =+(G7+H7)/2 -> 120251.62 | J7: =+(B7/I7)*100 -> 1.0627134
A8: =+A7+1 -> 2020 | B8: =+'Income Statement'!H10 -> 1297.44 | C8: =+'Balance Sheet'!G2+'Balance Sheet'!G3 -> 5642.6 | D8: =+'Balance Sheet'!H2+'Balance Sheet'!H3 -> 6806.62 | E8: =+(C8+D8)/2 -> 6224.61 | F8: =+(B8/E8)*100 -> 20.843716 | G8: =+'Balance Sheet'!G12 -> 130020.41 | H8: =+'Balance Sheet'!H12 -> 132223.85 | I8: =+(G8+H8)/2 -> 131122.13 | J8: =+(B8/I8)*100 -> 0.98948972
A9: =+A8+1 -> 2021 | B9: =+'Income Statement'!I10 -> 1360.87 | C9: =+'Balance Sheet'!H2+'Balance Sheet'!H3 -> 6806.62 | D9: =+'Balance Sheet'!I2+'Balance Sheet'!I3 -> 8639.79 | E9: =+(C9+D9)/2 -> 7723.205 | F9: =+(B9/E9)*100 -> 17.620534 | G9: =+'Balance Sheet'!H12 -> 132223.85 | H9: =+'Balance Sheet'!I12 -> 179655.04 | I9: =+(G9+H9)/2 -> 155939.45 | J9: =+(B9/I9)*100 -> 0.87269132
A10: =+A9+1 -> 2022 | B10: =+Table1[[#This Row],[Mar-22]] -> 1326.93 | C10: =+'Balance Sheet'!I2+'Balance Sheet'!I3 -> 8639.79 | D10: =+'Balance Sheet'!J2+'Balance Sheet'!J3 -> 15613.33 | E10: =+(C10+D10)/2 -> 12126.56 | F10: =+(B10/E10)*100 -> 10.942345 | G10: =+'Balance Sheet'!I12 -> 179655.04 | H10: =+'Balance Sheet'!J12 -> 230734.45 | I10: =+(G10+H10)/2 -> 205194.74 | J10: =+(B10/I10)*100 -> 0.64666861
A11: =+A10+1 -> 2023 | B11: =+'Income Statement'!K10 -> 1368.28 | C11: =+'Balance Sheet'!J2+'Balance Sheet'!J3 -> 15613.33 | D11: =+'Balance Sheet'!K2+'Balance Sheet'!K3 -> 12993.14 | E11: =+(C11+D11)/2 -> 14303.235 | F11: =+(B11/E11)*100 -> 9.5662275 | G11: =+'Balance Sheet'!J12 -> 230734.45 | H11: =+'Balance Sheet'!K12 -> 248069.25 | I11: =+(G11+H11)/2 -> 239401.85 | J11: =+(B11/I11)*100 -> 0.57154111
A12: =+A11+1 -> 2024 | B12: =+'Income Statement'!L10 -> 1574.08 | C12: =+'Balance Sheet'!K2+'Balance Sheet'!K3 -> 12993.14 | D12: =+'Balance Sheet'!L2+'Balance Sheet'!L3 -> 14666.35 | E12: =+(C12+D12)/2 -> 13829.745 | F12: =+(B12/E12)*100 -> 11.381844 | G12: =+'Balance Sheet'!K12 -> 248069.25 | H12: =+'Balance Sheet'!L12 -> 302686.95 | I12: =+(G12+H12)/2 -> 275378.1 | J12: =+(B12/I12)*100 -> 0.57160682
A14: Year | B14: Total Liabilities | C14: Total Equity | D14: Debt to Equity | F14: Year | G14: Revenue | H14: Revenue Growth Rate | J14: Year | K14: Net Profit | L14: Revenue | M14: Net Profit Margin
A15: 2014 | B15: =+'Balance Sheet'!B6 -> 52275 | C15: 1928 | D15: =+B15/C15 -> 27.113589 | F15: 2014 | G15: 17407 | H15: - | J15: 2014 | K15: 725 | L15: 17407 | M15: =+(K15/L15)*100 -> 4.1649911
A16: =+A15+1 -> 2015 | B16: =+'Balance Sheet'!C6 -> 69308.52 | C16: 2541.28 | D16: =+B16/C16 -> 27.273075 | F16: 2015 | G16: 27293 | H16: =+(G16-G15)/G15*100 -> 56.793244 | J16: 2015 | K16: 785.51 | L16: 27293 | M16: =+(K16/L16)*100 -> 2.878064
A17: =+A16+1 -> 2016 | B17: =+'Balance Sheet'!D6 -> 76544.38 | C17: 3103.49 | D17: =+B17/C17 -> 24.663969 | F17: 2016 | G17: 18248 | H17: =+(G17-G16)/G16*100 -> -33.140366 | J17: 2016 | K17: 816.79 | L17: 18248 | M17: =+(K17/L17)*100 -> 4.4760522
A18: =+A17+1 -> 2017 | B18: =+'Balance Sheet'!E6 -> 95096.57 | C18: 3826.32 | D18: =+B18/C18 -> 24.853272 | F18: 2017 | G18: 30785 | H18: =+(G18-G17)/G17*100 -> 68.70342 | J18: 2017 | K18: 886.92 | L18: 30785 | M18: =+(K18/L18)*100 -> 2.8810135
A19: =+A18+1 -> 2018 | B19: =+'Balance Sheet'!F6 -> 110482.82 | C19: 4705.11 | D19: =+B19/C19 -> 23.481453 | F19: 2018 | G19: 32541 | H19: =+(G19-G18)/G18*100 -> 5.7040767 | J19: 2018 | K19: 1107.2 | L19: 32541 | M19: =+(K19/L19)*100 -> 3.4024769
A20: =+A19+1 -> 2019 | B20: =+'Balance Sheet'!G6 -> 130020.41 | C20: 5642.6 | D20: =+B20/C20 -> 23.042642 | F20: 2019 | G20: 38990 | H20: =+(G20-G19)/G19*100 -> 19.818076 | J20: 2019 | K20: 1277.93 | L20: 38990 | M20: =+(K20/L20)*100 -> 3.277584
A21: =+A20+1 -> 2020 | B21: =+'Balance Sheet'!H6 -> 132223.85 | C21: 6806.62 | D21: =+B21/C21 -> 19.425772 | F21: 2020 | G21: 29749 | H21: =+(G21-G20)/G20*100 -> -23.700949 | J21: 2020 | K21: 1297.44 | L21: 29749 | M21: =+(K21/L21)*100 -> 4.3612895
A22: =+A21+1 -> 2021 | B22: =+'Balance Sheet'!I6 -> 179655.04 | C22: 8639.79 | D22: =+B22/C22 -> 20.793913 | F22: 2021 | G22: 71973 | H22: =+(G22-G21)/G21*100 -> 141.93418 | J22: 2021 | K22: 1360.87 | L22: 71973 | M22: =+(K22/L22)*100 -> 1.8908063
A23: =+A22+1 -> 2022 | B23: =+'Balance Sheet'!J6 -> 230734.45 | C23: 15613.33 | D23: =+B23/C23 -> 14.778042 | F23: 2022 | G23: 67892 | H23: =+(G23-G22)/G22*100 -> -5.6701819 | J23: 2022 | K23: 1326.93 | L23: 67892 | M23: =+(K23/L23)*100 -> 1.9544718
A24: =+A23+1 -> 2023 | B24: =+'Balance Sheet'!K6 -> 248069.25 | C24: 12993.14 | D24: =+B24/C24 -> 19.092325 | F24: 2023 | G24: 71644 | H24: =+(G24-G23)/G23*100 -> 5.5264243 | J24: 2023 | K24: 1368.28 | L24: 71644 | M24: =+(K24/L24)*100 -> 1.9098319
A25: =+A24+1 -> 2024 | B25: =+'Balance Sheet'!L6 -> 302686.95 | C25: =+'Balance Sheet'!L2+'Balance Sheet'!L3 -> 14666.35 | D25: =+B25/C25 -> 20.638192 | F25: 2024 | G25: 102007 | H25: =+(G25-G24)/G24*100 -> 42.380381 | J25: 2024 | K25: 1574.08 | L25: 102007 | M25: =+(K25/L25)*100 -> 1.5431098

Sheet Dashboard
